[{"text": "Oh the wind [SPK]whistles[/SPK] down", "image": "http://farm8.staticflickr.com/7329/12862087173_af78dfa143.jpg", "end_time": 13930, "keyword": ["whistles", "NNS"], "begin_time": 12650}, {"text": "The cold dark street [SPK]tonight[/SPK]", "image": "http://farm3.staticflickr.com/2920/13646957914_1593236ee7.jpg", "end_time": 17390, "keyword": ["tonight", "NN"], "begin_time": 13930}, {"text": "And the people they were dancing to the music [SPK]vibe[/SPK]", "image": "http://farm4.staticflickr.com/3698/13652280993_5f33159472.jpg", "end_time": 22010, "keyword": ["vibe", "NN"], "begin_time": 17390}, {"text": "And the boys chase the girls with the curls in their [SPK]hair[/SPK]", "image": "http://farm3.staticflickr.com/2826/13657177784_9e2a0943f3.jpg", "end_time": 24850, "keyword": ["hair", "NN"], "begin_time": 22010}, {"text": "While the shy tormented youth sit [SPK]way[/SPK] over there", "image": "http://farm8.staticflickr.com/7137/13656599654_6ce7336f17.jpg", "end_time": 27230, "keyword": ["way", "NN"], "begin_time": 24850}, {"text": "And the [SPK]songs[/SPK] they get louder", "image": "http://farm4.staticflickr.com/3811/13656705525_4cd2466e71.jpg", "end_time": 28780, "keyword": ["songs", "NNS"], "begin_time": 27230}, {"text": "Each one [SPK]better[/SPK] than before", "image": "http://farm8.staticflickr.com/7449/13652361915_980f3b813c.jpg", "end_time": 30260, "keyword": ["better", "JJR"], "begin_time": 28780}, {"text": "And you're singing the [SPK]songs[/SPK]", "image": "http://farm4.staticflickr.com/3811/13656705525_4cd2466e71.jpg", "end_time": 33070, "keyword": ["songs", "NNS"], "begin_time": 30260}, {"text": "Thinking this is the [SPK]life[/SPK]", "image": "http://farm3.staticflickr.com/2871/13657605504_8d1de304da.jpg", "end_time": 34530, "keyword": ["life", "NN"], "begin_time": 33070}, {"text": "And you wake up in the morning and your head feels twice the [SPK]size[/SPK]", "image": "http://farm3.staticflickr.com/2937/13655436443_caeceb76db.jpg", "end_time": 36880, "keyword": ["size", "NN"], "begin_time": 34530}, {"text": "Where you [SPK]go[/SPK]nna go? Where you gonna go?", "image": "http://farm3.staticflickr.com/2921/13656648233_f0ca09221d.jpg", "end_time": 39070, "keyword": ["go", "VB"], "begin_time": 36880}, {"text": "Where you gonna sleep [SPK]tonight[/SPK]?", "image": "http://farm3.staticflickr.com/2920/13646957914_1593236ee7.jpg", "end_time": 42060, "keyword": ["tonight", "NN"], "begin_time": 39070}, {"text": "And you're singing the [SPK]songs[/SPK]", "image": "http://farm4.staticflickr.com/3811/13656705525_4cd2466e71.jpg", "end_time": 43360, "keyword": ["songs", "NNS"], "begin_time": 42060}, {"text": "Thinking this is the [SPK]life[/SPK]", "image": "http://farm3.staticflickr.com/2871/13657605504_8d1de304da.jpg", "end_time": 44750, "keyword": ["life", "NN"], "begin_time": 43360}, {"text": "And you wake up in the morning and your head feels twice the [SPK]size[/SPK]", "image": "http://farm3.staticflickr.com/2937/13655436443_caeceb76db.jpg", "end_time": 46360, "keyword": ["size", "NN"], "begin_time": 44750}, {"text": "Where you [SPK]go[/SPK]nna go? Where you gonna go?", "image": "http://farm3.staticflickr.com/2921/13656648233_f0ca09221d.jpg", "end_time": 49220, "keyword": ["go", "VB"], "begin_time": 46360}, {"text": "Where you gonna sleep [SPK]tonight[/SPK]?", "image": "http://farm3.staticflickr.com/2920/13646957914_1593236ee7.jpg", "end_time": 51900, "keyword": ["tonight", "NN"], "begin_time": 49220}, {"text": "Where you gonna sleep [SPK]tonight[/SPK]?", "image": "http://farm3.staticflickr.com/2920/13646957914_1593236ee7.jpg", "end_time": 57840, "keyword": ["tonight", "NN"], "begin_time": 51900}, {"text": "So you're heading down the road in your [SPK]taxi[/SPK] for four", "image": "http://farm8.staticflickr.com/7237/13656376573_2de9f0359a.jpg", "end_time": 65430, "keyword": ["taxi", "NN"], "begin_time": 57840}, {"text": "And you're waiting outside Jimmy's front [SPK]door[/SPK]", "image": "http://farm8.staticflickr.com/7393/13657087343_50e6fcfc36.jpg", "end_time": 67760, "keyword": ["door", "NN"], "begin_time": 65430}, {"text": "But nobody's in and nobody's [SPK]home[/SPK] 'til four", "image": "http://farm8.staticflickr.com/7178/13657112045_2952992d9d.jpg", "end_time": 72260, "keyword": ["home", "NN"], "begin_time": 67760}, {"text": "So you're sitting there with [SPK]nothing[/SPK] to do", "image": "http://farm8.staticflickr.com/7362/13654377884_98e50d0518.jpg", "end_time": 75400, "keyword": ["nothing", "NN"], "begin_time": 72260}, {"text": "Talking about Robert Riger and his motley [SPK]crew[/SPK]", "image": "http://farm8.staticflickr.com/7088/13656657245_737c45747e.jpg", "end_time": 77650, "keyword": ["crew", "NN"], "begin_time": 75400}, {"text": "And where you're gonna go and where you're gonna sleep [SPK]tonight[/SPK]", "image": "http://farm3.staticflickr.com/2920/13646957914_1593236ee7.jpg", "end_time": 81750, "keyword": ["tonight", "NN"], "begin_time": 77650}, {"text": "And you're singing the [SPK]songs[/SPK]", "image": "http://farm4.staticflickr.com/3811/13656705525_4cd2466e71.jpg", "end_time": 83670, "keyword": ["songs", "NNS"], "begin_time": 81750}, {"text": "Thinking this is the [SPK]life[/SPK]", "image": "http://farm3.staticflickr.com/2871/13657605504_8d1de304da.jpg", "end_time": 85040, "keyword": ["life", "NN"], "begin_time": 83670}, {"text": "And you wake up in the morning and your head feels twice the [SPK]size[/SPK]", "image": "http://farm3.staticflickr.com/2937/13655436443_caeceb76db.jpg", "end_time": 87430, "keyword": ["size", "NN"], "begin_time": 85040}, {"text": "Where you [SPK]go[/SPK]nna go? Where you gonna go?", "image": "http://farm3.staticflickr.com/2921/13656648233_f0ca09221d.jpg", "end_time": 89780, "keyword": ["go", "VB"], "begin_time": 87430}, {"text": "Where you gonna sleep [SPK]tonight[/SPK]?", "image": "http://farm3.staticflickr.com/2920/13646957914_1593236ee7.jpg", "end_time": 92820, "keyword": ["tonight", "NN"], "begin_time": 89780}, {"text": "And you're singing the [SPK]songs[/SPK]", "image": "http://farm4.staticflickr.com/3811/13656705525_4cd2466e71.jpg", "end_time": 94180, "keyword": ["songs", "NNS"], "begin_time": 92820}, {"text": "Thinking this is the [SPK]life[/SPK]", "image": "http://farm3.staticflickr.com/2871/13657605504_8d1de304da.jpg", "end_time": 95310, "keyword": ["life", "NN"], "begin_time": 94180}, {"text": "And you wake up in the morning and your head feels twice the [SPK]size[/SPK]", "image": "http://farm3.staticflickr.com/2937/13655436443_caeceb76db.jpg", "end_time": 97540, "keyword": ["size", "NN"], "begin_time": 95310}, {"text": "Where you [SPK]go[/SPK]nna go? Where you gonna go?", "image": "http://farm3.staticflickr.com/2921/13656648233_f0ca09221d.jpg", "end_time": 99680, "keyword": ["go", "VB"], "begin_time": 97540}, {"text": "Where you gonna sleep [SPK]tonight[/SPK]?", "image": "http://farm3.staticflickr.com/2920/13646957914_1593236ee7.jpg", "end_time": 102730, "keyword": ["tonight", "NN"], "begin_time": 99680}, {"text": "Where you gonna sleep [SPK]tonight[/SPK]?", "image": "http://farm3.staticflickr.com/2920/13646957914_1593236ee7.jpg", "end_time": 104650, "keyword": ["tonight", "NN"], "begin_time": 102730}, {"text": "And you're singing the [SPK]songs[/SPK]", "image": "http://farm4.staticflickr.com/3811/13656705525_4cd2466e71.jpg", "end_time": 124340, "keyword": ["songs", "NNS"], "begin_time": 104650}, {"text": "Thinking this is the [SPK]life[/SPK]", "image": "http://farm3.staticflickr.com/2871/13657605504_8d1de304da.jpg", "end_time": 125460, "keyword": ["life", "NN"], "begin_time": 124340}, {"text": "And you wake up in the morning and your head feels twice the [SPK]size[/SPK]", "image": "http://farm3.staticflickr.com/2937/13655436443_caeceb76db.jpg", "end_time": 127950, "keyword": ["size", "NN"], "begin_time": 125460}, {"text": "Where you [SPK]go[/SPK]nna go? Where you gonna go?", "image": "http://farm3.staticflickr.com/2921/13656648233_f0ca09221d.jpg", "end_time": 130030, "keyword": ["go", "VB"], "begin_time": 127950}, {"text": "Where you gonna sleep [SPK]tonight[/SPK]?", "image": "http://farm3.staticflickr.com/2920/13646957914_1593236ee7.jpg", "end_time": 133160, "keyword": ["tonight", "NN"], "begin_time": 130030}, {"text": "And you're singing the [SPK]songs[/SPK]", "image": "http://farm4.staticflickr.com/3811/13656705525_4cd2466e71.jpg", "end_time": 134460, "keyword": ["songs", "NNS"], "begin_time": 133160}, {"text": "Thinking this is the [SPK]life[/SPK]", "image": "http://farm3.staticflickr.com/2871/13657605504_8d1de304da.jpg", "end_time": 135800, "keyword": ["life", "NN"], "begin_time": 134460}, {"text": "And you wake up in the morning and your head feels twice the [SPK]size[/SPK]", "image": "http://farm3.staticflickr.com/2937/13655436443_caeceb76db.jpg", "end_time": 137870, "keyword": ["size", "NN"], "begin_time": 135800}, {"text": "Where you [SPK]go[/SPK]nna go? Where you gonna go?", "image": "http://farm3.staticflickr.com/2921/13656648233_f0ca09221d.jpg", "end_time": 140210, "keyword": ["go", "VB"], "begin_time": 137870}, {"text": "Where you gonna sleep [SPK]tonight[/SPK]?", "image": "http://farm3.staticflickr.com/2920/13646957914_1593236ee7.jpg", "end_time": 142970, "keyword": ["tonight", "NN"], "begin_time": 140210}, {"text": "And you're singing the [SPK]songs[/SPK]", "image": "http://farm4.staticflickr.com/3811/13656705525_4cd2466e71.jpg", "end_time": 144430, "keyword": ["songs", "NNS"], "begin_time": 142970}, {"text": "Thinking this is the [SPK]life[/SPK]", "image": "http://farm3.staticflickr.com/2871/13657605504_8d1de304da.jpg", "end_time": 145960, "keyword": ["life", "NN"], "begin_time": 144430}, {"text": "And you wake up in the morning and your head feels twice the [SPK]size[/SPK]", "image": "http://farm3.staticflickr.com/2937/13655436443_caeceb76db.jpg", "end_time": 148190, "keyword": ["size", "NN"], "begin_time": 145960}, {"text": "Where you [SPK]go[/SPK]nna go? Where you gonna go?", "image": "http://farm3.staticflickr.com/2921/13656648233_f0ca09221d.jpg", "end_time": 150370, "keyword": ["go", "VB"], "begin_time": 148190}, {"text": "Where you gonna sleep [SPK]tonight[/SPK]?", "image": "http://farm3.staticflickr.com/2920/13646957914_1593236ee7.jpg", "end_time": 153030, "keyword": ["tonight", "NN"], "begin_time": 150370}, {"text": "And you're singing the [SPK]songs[/SPK]", "image": "http://farm4.staticflickr.com/3811/13656705525_4cd2466e71.jpg", "end_time": 154610, "keyword": ["songs", "NNS"], "begin_time": 153030}, {"text": "Thinking this is the [SPK]life[/SPK]", "image": "http://farm3.staticflickr.com/2871/13657605504_8d1de304da.jpg", "end_time": 155870, "keyword": ["life", "NN"], "begin_time": 154610}, {"text": "And you wake up in the morning and your head feels twice the [SPK]size[/SPK]", "image": "http://farm3.staticflickr.com/2937/13655436443_caeceb76db.jpg", "end_time": 158280, "keyword": ["size", "NN"], "begin_time": 155870}, {"text": "Where you [SPK]go[/SPK]nna go? Where you gonna go?", "image": "http://farm3.staticflickr.com/2921/13656648233_f0ca09221d.jpg", "end_time": 160310, "keyword": ["go", "VB"], "begin_time": 158280}, {"text": "Where you gonna sleep [SPK]tonight[/SPK]?", "image": "http://farm3.staticflickr.com/2920/13646957914_1593236ee7.jpg", "end_time": 163960, "keyword": ["tonight", "NN"], "begin_time": 160310}, {"text": "Where you gonna sleep [SPK]tonight[/SPK]?", "image": "http://farm3.staticflickr.com/2920/13646957914_1593236ee7.jpg", "end_time": 169840, "keyword": ["tonight", "NN"], "begin_time": 163960}]